phi_cloud_server/__init__.py
phi_cloud_server/__main__.py
phi_cloud_server/config.py
phi_cloud_server/db.py
phi_cloud_server/db0.py
phi_cloud_server/decorators.py
phi_cloud_server/main.py
phi_cloud_server/models.py
phi_cloud_server/dns/__init__.py
phi_cloud_server/dns/__main__.py
phi_cloud_server/dns/generate_certs.py
phi_cloud_server/utils/__init__.py
phi_cloud_server/utils/datetime.py
phi_cloud_server/utils/main.py
phi_cloud_server/utils/random.py
phi_cloud_server-0.1.2a3.dist-info/licenses/LICENSE
phi_cloud_server-0.1.2a3.dist-info/licenses/LICENSE-cn
phi_cloud_server-0.1.2a3.dist-info/METADATA
phi_cloud_server-0.1.2a3.dist-info/WHEEL
phi_cloud_server-0.1.2a3.dist-info/entry_points.txt
phi_cloud_server-0.1.2a3.dist-info/top_level.txt
phi_cloud_server-0.1.2a3.dist-info/RECORD
