Metadata-Version: 2.4
Name: phi_cloud_server
Version: 0.1.2a3
Summary: Phigros云存档服务器。
Author-email: Shua-github <CHA_shua@outlook.com>
License: Software License Agreement
Requires-Python: >=3.9
License-File: LICENSE
License-File: LICENSE-cn
Requires-Dist: fastapi>=0.115.12
Requires-Dist: uvicorn>=0.34.0
Requires-Dist: pydantic>=2.11.2
Requires-Dist: PyYAML>=6.0.2
Requires-Dist: tortoise-orm>=0.24.2
Requires-Dist: ruamel-yaml>=0.18.10
Provides-Extra: dns
Requires-Dist: dnslib>=0.9.26; extra == "dns"
Requires-Dist: psutil>=7.0.0; extra == "dns"
Requires-Dist: cryptography>=44.0.2; extra == "dns"
Dynamic: license-file
